ColdTOFU/ATSIFIO64.dll
ColdTOFU/AndorSifReader.py
ColdTOFU/Helvetica_bright.mplstyle
ColdTOFU/Images.py
ColdTOFU/__init__.py
ColdTOFU/fits.py
ColdTOFU/jupyterTools.py
ColdTOFU/numberOfAtoms.py
ColdTOFU/picoMatTools.py
ColdTOFU/rcParams.json
ColdTOFU/scientific_serif.mplstyle
ColdTOFU/sigma.py
ColdTOFU/spectrum.py
ColdTOFU/Physics/__init__.py
ColdTOFU/Physics/allenDeviation.py
ColdTOFU/Physics/basisMatrices.py
ColdTOFU/Physics/beams.py
ColdTOFU/Physics/createAndDestroy.py
ColdTOFU/Physics/spinInDickeBasis.py
ColdTOFU-0.1.4.dist-info/LICENCE
ColdTOFU-0.1.4.dist-info/METADATA
ColdTOFU-0.1.4.dist-info/WHEEL
ColdTOFU-0.1.4.dist-info/top_level.txt
ColdTOFU-0.1.4.dist-info/RECORD
